yt_audio/YTAudio.py
yt_audio/arguments.py
yt_audio/common.py
yt_audio/version.py
yt_audio-0.1.dist-info/LICENSE
yt_audio-0.1.dist-info/METADATA
yt_audio-0.1.dist-info/WHEEL
yt_audio-0.1.dist-info/entry_points.txt
yt_audio-0.1.dist-info/top_level.txt
yt_audio-0.1.dist-info/RECORD
