Metadata-Version: 2.1
Name: yt-audio
Version: 0.1
Summary: A simple, configurable youtube-dl wrapper to download and manage youtube audio (with added features)
Home-page: https://github.com/pseudoroot/yt-audio
Author: pseudoroot
Author-email: pseudoroot@protonmail.ch
License: MIT
Platform: UNKNOWN
Classifier: Programming Language :: Python :: 3
Classifier: License :: OSI Approved :: MIT License
Classifier: Operating System :: OS Independent
Classifier: Environment :: Console
Classifier: Topic :: Multimedia :: Sound/Audio
Classifier: License :: OSI Approved :: MIT License
Requires-Python: >=3.5
